README.rst
setup.py
bigstack/__init__.py
bigstack/bigstack.py
bigstack.egg-info/PKG-INFO
bigstack.egg-info/SOURCES.txt
bigstack.egg-info/dependency_links.txt
bigstack.egg-info/top_level.txt