Metadata-Version: 1.0
Name: bigstack
Version: 0.1.1
Summary: Decorator that increase the stack size for a function
Home-page: http://github.com/enricobacis/bigstack
Author: Enrico Bacis
Author-email: enrico.bacis@gmail.com
License: MIT
Keywords: stack stacksize recursive recursion decorator
Platform: UNKNOWN
